README.md
setup.cfg
setup.py
cartodb_dashboard/__init__.py
cartodb_dashboard/cartodb_dashboard.py
cartodb_dashboard.egg-info/PKG-INFO
cartodb_dashboard.egg-info/SOURCES.txt
cartodb_dashboard.egg-info/dependency_links.txt
cartodb_dashboard.egg-info/requires.txt
cartodb_dashboard.egg-info/top_level.txt