Metadata-Version: 1.1
Name: cartodb-dashboard
Version: 0.2.12
Summary: Provides access to the cartodb dashboard
Home-page: https://github.com/realestate-com-au/cartodb-dashboard-python
Author: Simon Hope
Author-email: shope@geoplex.com.au
License: UNKNOWN
Download-URL: https://github.com/realestate-com-au/cartodb-dashboard-python/tarball/0.2.12
Platform: UNKNOWN
Requires: simplejson
Requires: httplib2
